iotree/__init__.py
iotree/__main__.py
iotree/cli/__init__.py
iotree/cli/run.py
iotree/config/local-config.json
iotree/config/symbols-extras.json
iotree/config/symbols.json
iotree/config/themes.json
iotree/config/user-settings.json
iotree/core/__init__.py
iotree/core/io/__init__.py
iotree/core/io/internals.py
iotree/core/io/reader.py
iotree/core/io/serialize.py
iotree/core/io/writer.py
iotree/core/render/__init__.py
iotree/core/render/demo.py
iotree/core/render/funcs.py
iotree/core/render/tables.py
iotree/core/render/theme.py
iotree/core/render/trees.py
iotree/examples/example-hard.html
iotree/examples/example.html
iotree/examples/example.json
iotree/examples/example.toml
iotree/examples/example.xml
iotree/examples/example.yaml
iotree/utils/__init__.py
iotree/utils/paths.py
iotree-0.1.22.post1.dist-info/entry_points.txt
iotree-0.1.22.post1.dist-info/METADATA
iotree-0.1.22.post1.dist-info/WHEEL
iotree-0.1.22.post1.dist-info/RECORD
