Metadata-Version: 2.1
Name: iotree
Version: 0.1.22.post1
Summary: A lightweight CLI + lib that allows you to perform basic IO tasks and display your content as rich trees and tables.
Author: Arno V
Author-email: bcda0276@gmail.com
Requires-Python: >=3.8,<4.0
Classifier: Programming Language :: Python :: 3
Classifier: Programming Language :: Python :: 3.8
Classifier: Programming Language :: Python :: 3.9
Classifier: Programming Language :: Python :: 3.10
Classifier: Programming Language :: Python :: 3.11
Requires-Dist: httpx (>=0.22.0,<0.23.0)
Requires-Dist: orjson (>=3.8.5,<4.0.0)
Requires-Dist: pytest (>=7.2.0,<8.0.0)
Requires-Dist: pyyaml (>=6.0,<7.0)
Requires-Dist: rich (>=10.11.0,<13.0.0)
Requires-Dist: soup2dict (>=2.1.0,<3.0.0)
Requires-Dist: toml (>=0.10.2,<0.11.0)
Requires-Dist: typer[all] (>=0.7.0,<0.8.0)
Requires-Dist: xmltodict (>=0.13.0,<0.14.0)
